aiogram_mediagroup_handle/__init__.py
aiogram_mediagroup_handle/_types.py
aiogram_mediagroup_handle/core.py
aiogram_mediagroup_handle/filter.py
aiogram_mediagroup_handle/media.py
aiogram_mediagroup_handle/middleware.py
aiogram_mediagroup_handle/py.typed
aiogram_mediagroup_handle/util.py
aiogram_mediagroup_handle-0.1.3.dist-info/METADATA
aiogram_mediagroup_handle-0.1.3.dist-info/WHEEL
aiogram_mediagroup_handle-0.1.3.dist-info/licenses/LICENSE
aiogram_mediagroup_handle-0.1.3.dist-info/RECORD
