Metadata-Version: 2.4
Name: aiogram-mediagroup-handle
Version: 0.1.3
Summary: aiogram media group observer
Project-URL: Repository, https://github.com/andrei-samofalov/aiogram-mediagroup
Author-email: andrei-samofalov <andrei.e.samofalov@gmail.com>
License-File: LICENSE
Keywords: aiogram,album,media group,storage
Requires-Python: >=3.11
Requires-Dist: aiogram>=3
